[{"District":"Kolkata","Hospital Name":"AMRI Salt Lake","Total beds":"25","Vacant beds":"0","Last Updated":"29.04.2021"},{"District":"Kolkata","Hospital Name":"CNMCH","Total beds":"50","Vacant beds":"0","Last Updated":"29.04.2021"},{"District":"Kolkata","Hospital Name":"CNCI","Total beds":"425","Vacant beds":"61","Last Updated":"29.04.2021"},{"District":"Kolkata","Hospital Name":"Desun Hospital, Kolkata","Total beds":"25","Vacant beds":"17","Last Updated":"29.04.2021"},{"District":"Kolkata","Hospital Name":"ID BG","Total beds":"315","Vacant beds":"41","Last Updated":"29.04.2021"},{"District":"Kolkata","Hospital Name":"K. S. Roy TB Hospital","Total beds":"130","Vacant beds":"55","Last Updated":"29.04.2021"},{"District":"Kolkata","Hospital Name":"Kolkata Medical College","Total beds":"305","Vacant beds":"36","Last Updated":"29.04.2021"},{"District":"Kolkata","Hospital Name":"KPC Medical College","Total beds":"200","Vacant beds":"0","Last Updated":"29.04.2021"},{"District":"Kolkata","Hospital Name":"M R Bangur DH & SSH","Total beds":"603","Vacant beds":"113","Last Updated":"29.04.2021"},{"District":"Kolkata","Hospital Name":"N R S Medical College & Hospital","Total beds":"110","Vacant beds":"0","Last Updated":"29.04.2021"},{"District":"Kolkata","Hospital Name":"R G Kar MCH","Total beds":"110","Vacant beds":"31","Last Updated":"29.04.2021"},{"District":"Kolkata","Hospital Name":"Shambhunath Pandit Hospital","Total beds":"90","Vacant beds":"6","Last Updated":"29.04.2021"},{"District":"Alipurduar","Hospital Name":"Alipurduar DH","Total beds":"15","Vacant beds":"15","Last Updated":"29.04.2021"},{"District":"Alipurduar","Hospital Name":"Integrated Ayush (COVID 19) Hospital,\rTapsikhata","Total beds":"110","Vacant beds":"78","Last Updated":"29.04.2021"},{"District":"Bankura","Hospital Name":"Bankura SMCH","Total beds":"100","Vacant beds":"99","Last Updated":"29.04.2021"},{"District":"Bankura","Hospital Name":"Onda SSH","Total beds":"250","Vacant beds":"81","Last Updated":"29.04.2021"},{"District":"Birbhum","Hospital Name":"Adeen Healthcare Private Ltd.","Total beds":"87","Vacant beds":"87","Last Updated":"29.04.2021"},{"District":"Birbhum","Hospital Name":"Glocal Hospital, Birbhum","Total beds":"90","Vacant beds":"21","Last Updated":"29.04.2021"},{"District":"Birbhum","Hospital Name":"Niramoy TB Sanitorium","Total beds":"150","Vacant beds":"150","Last Updated":"29.04.2021"},{"District":"Birbhum","Hospital Name":"Rampurhat Govt Medical College &\rHospital","Total beds":"160","Vacant beds":"84","Last Updated":"29.04.2021"},{"District":"District","Hospital Name":"Name of CoVid Hospital","Total beds":"Total\rBeds","Vacant beds":"Vacant\rBeds","Last Updated":"29.04.2021"},{"District":"Coochbehar","Hospital Name":"Cooch Behar MJN MCH","Total beds":"90","Vacant beds":"90","Last Updated":"29.04.2021"},{"District":"Coochbehar","Hospital Name":"Dinhata SDH","Total beds":"32","Vacant beds":"24","Last Updated":"29.04.2021"},{"District":"Dakshin Dinajpur","Hospital Name":"Gangarampur SDH","Total beds":"41","Vacant beds":"40","Last Updated":"29.04.2021"},{"District":"Dakshin Dinajpur","Hospital Name":"Natya Utkarsha Kendra","Total beds":"80","Vacant beds":"30","Last Updated":"29.04.2021"},{"District":"Darjeeling","Hospital Name":"NBMCH 1","Total beds":"110","Vacant beds":"43","Last Updated":"29.04.2021"},{"District":"Hooghly","Hospital Name":"Arambagh SSH96","Total beds":"64","Vacant beds":null,"Last Updated":"29.04.2021"},{"District":"Hooghly","Hospital Name":"Chandannagar SDH, Covid Isolation Unit","Total beds":"150","Vacant beds":"42","Last Updated":"29.04.2021"},{"District":"Hooghly","Hospital Name":"ESI Gourhati","Total beds":"50","Vacant beds":"46","Last Updated":"29.04.2021"},{"District":"Hooghly","Hospital Name":"ESI Hospital, Bandel","Total beds":"150","Vacant beds":"65","Last Updated":"29.04.2021"},{"District":"Hooghly","Hospital Name":"Imambara DH","Total beds":"151","Vacant beds":"114","Last Updated":"29.04.2021"},{"District":"Hooghly","Hospital Name":"Singur Trauma Care Centre","Total beds":"100","Vacant beds":"54","Last Updated":"29.04.2021"},{"District":"Hooghly","Hospital Name":"Sreerampur Walsh Hospital","Total beds":"50","Vacant beds":"2","Last Updated":"29.04.2021"},{"District":"Hooghly","Hospital Name":"Uttarpara SGH","Total beds":"40","Vacant beds":"10","Last Updated":"29.04.2021"},{"District":"Howrah","Hospital Name":"ESI Hospital, Baltikuri","Total beds":"400","Vacant beds":"229","Last Updated":"29.04.2021"},{"District":"Howrah","Hospital Name":"Satyabala IDH","Total beds":"25","Vacant beds":"0","Last Updated":"29.04.2021"},{"District":"Howrah","Hospital Name":"TLJ Hospital","Total beds":"250","Vacant beds":"103","Last Updated":"29.04.2021"},{"District":"Jalpaiguri","Hospital Name":"Biswabangla Krirangan (Sports\rComplex)","Total beds":"300","Vacant beds":"110","Last Updated":"29.04.2021"},{"District":"Jhargram","Hospital Name":"Jhargram Night Shelter","Total beds":"75","Vacant beds":"75","Last Updated":"29.04.2021"},{"District":"Jhargram","Hospital Name":"Jhargram Working Women Hostel","Total beds":"75","Vacant beds":"75","Last Updated":"29.04.2021"},{"District":"Kalimpong","Hospital Name":"Triveni Hospital","Total beds":"180","Vacant beds":"105","Last Updated":"29.04.2021"},{"District":"Malda","Hospital Name":"Malda MCH Trauma Care Centre Covid","Total beds":"osp1i5ta0l","Vacant beds":"27","Last Updated":"29.04.2021"},{"District":"Murshidabad","Hospital Name":"Domkol SDH","Total beds":"20","Vacant beds":"19","Last Updated":"29.04.2021"},{"District":"District","Hospital Name":"Name of CoVid Hospital","Total beds":"Total\rBeds","Vacant beds":"Vacant\rBeds","Last Updated":"29.04.2021"},{"District":"Murshidabad","Hospital Name":"Khristio Seba Sadan","Total beds":"100","Vacant beds":"41","Last Updated":"29.04.2021"},{"District":"Murshidabad","Hospital Name":"Old Matri Sadan Hospital","Total beds":"300","Vacant beds":"150","Last Updated":"29.04.2021"},{"District":"Nadia","Hospital Name":"Glocal Hospital, Nadia","Total beds":"10","Vacant beds":"10","Last Updated":"29.04.2021"},{"District":"Nadia","Hospital Name":"JNM MCH","Total beds":"80","Vacant beds":"80","Last Updated":"29.04.2021"},{"District":"Nadia","Hospital Name":"Netaji Subhas Sanitorium, Kalyani","Total beds":"300","Vacant beds":"14","Last Updated":"29.04.2021"},{"District":"Nadia","Hospital Name":"Shaktinagar Campus, Nadia DH","Total beds":"60","Vacant beds":"60","Last Updated":"29.04.2021"},{"District":"North 24 Pgs","Hospital Name":"Al Amin Gopalpur Nursing Home","Total beds":"10","Vacant beds":"10","Last Updated":"29.04.2021"},{"District":"North 24 Pgs","Hospital Name":"Basirhat District Hospital","Total beds":"35","Vacant beds":"0","Last Updated":"29.04.2021"},{"District":"North 24 Pgs","Hospital Name":"Ashoknagar SGH","Total beds":"80","Vacant beds":"0","Last Updated":"29.04.2021"},{"District":"North 24 Pgs","Hospital Name":"Baranagar SGH","Total beds":"80","Vacant beds":"43","Last Updated":"29.04.2021"},{"District":"North 24 Pgs","Hospital Name":"Bongaon SDH","Total beds":"50","Vacant beds":"18","Last Updated":"29.04.2021"},{"District":"North 24 Pgs","Hospital Name":"COM & Sagar Datta Hospital","Total beds":"160","Vacant beds":"0","Last Updated":"29.04.2021"},{"District":"North 24 Pgs","Hospital Name":"GNRC","Total beds":"33","Vacant beds":"14","Last Updated":"29.04.2021"},{"District":"North 24 Pgs","Hospital Name":"Gobardanga RH Covid Hospital","Total beds":"50","Vacant beds":"23","Last Updated":"29.04.2021"},{"District":"North 24 Pgs","Hospital Name":"Naihati SGH","Total beds":"90","Vacant beds":"3","Last Updated":"29.04.2021"},{"District":"North 24 Pgs","Hospital Name":"Nehru Memorial Techno Global","Total beds":"50","Vacant beds":"0","Last Updated":"29.04.2021"},{"District":"North 24 Pgs","Hospital Name":"Panihati SGH","Total beds":"150","Vacant beds":"124","Last Updated":"29.04.2021"},{"District":"North 24 Pgs","Hospital Name":"Sree Balaram Seva Mandir SGH","Total beds":"80","Vacant beds":"2","Last Updated":"29.04.2021"},{"District":"Paschim Bardhaman","Hospital Name":"Sanaka Hospital","Total beds":"200","Vacant beds":"78","Last Updated":"29.04.2021"},{"District":"Paschim Medinipur","Hospital Name":"AYUSH Corona Hospital, Paschim\rMedinipore","Total beds":"100","Vacant beds":"100","Last Updated":"29.04.2021"},{"District":"Paschim Medinipur","Hospital Name":"AYUSH Satellite Hospital","Total beds":"100","Vacant beds":"100","Last Updated":"29.04.2021"},{"District":"Paschim Medinipur","Hospital Name":"Debra RH Covid Hospital","Total beds":"40","Vacant beds":"40","Last Updated":"29.04.2021"},{"District":"District","Hospital Name":"Name of CoVid Hospital","Total beds":"Total\rBeds","Vacant beds":"Vacant\rBeds","Last Updated":"29.04.2021"},{"District":"Paschim Medinipur","Hospital Name":"Ghatal SDH Covid Hospital","Total beds":"80","Vacant beds":"29","Last Updated":"29.04.2021"},{"District":"Paschim Medinipur","Hospital Name":"Kharagpur SDH Corona Hospital","Total beds":"50","Vacant beds":"7","Last Updated":"29.04.2021"},{"District":"Paschim Medinipur","Hospital Name":"Midnapore Medical College Hospital","Total beds":"30","Vacant beds":"8","Last Updated":"29.04.2021"},{"District":"Paschim Medinipur","Hospital Name":"Salboni SSH","Total beds":"200","Vacant beds":"122","Last Updated":"29.04.2021"},{"District":"Purba Burdwan","Hospital Name":"Bardhaman Medical College & Hospital","Total beds":"67","Vacant beds":"0","Last Updated":"29.04.2021"},{"District":"Purba Burdwan","Hospital Name":"Kalna SDH","Total beds":"46","Vacant beds":"33","Last Updated":"29.04.2021"},{"District":"Purba Burdwan","Hospital Name":"Krishi Bhavan Covid Hospital","Total beds":"100","Vacant beds":"30","Last Updated":"29.04.2021"},{"District":"Purba Medinipore","Hospital Name":"Chandipur Multi Speciality Hospital","Total beds":"136","Vacant beds":"0","Last Updated":"29.04.2021"},{"District":"Purba Medinipore","Hospital Name":"Nandigram SSH","Total beds":"40","Vacant beds":"34","Last Updated":"29.04.2021"},{"District":"Purulia","Hospital Name":"Hatuara SSH","Total beds":"93","Vacant beds":"0","Last Updated":"29.04.2021"},{"District":"South 24 Parganas","Hospital Name":"Diamond Harbour GMCH","Total beds":"158","Vacant beds":"39","Last Updated":"29.04.2021"},{"District":"South 24 Parganas","Hospital Name":"ESIC Medical College","Total beds":"90","Vacant beds":"88","Last Updated":"29.04.2021"},{"District":"South 24 Parganas","Hospital Name":"Baruipur SDH","Total beds":"100","Vacant beds":"49","Last Updated":"29.04.2021"},{"District":"South 24 Parganas","Hospital Name":"Canning Covid Hospital (Stadium)","Total beds":"55","Vacant beds":"10","Last Updated":"29.04.2021"},{"District":"Uttar Dinajpur","Hospital Name":"Islampur Urdu Academy","Total beds":"100","Vacant beds":"69","Last Updated":"29.04.2021"},{"District":"Uttar Dinajpur","Hospital Name":"Mikki Megha Hospital","Total beds":"50","Vacant beds":"14","Last Updated":"29.04.2021"},{"District":"Uttar Dinajpur","Hospital Name":"Raiganj Govt MCH","Total beds":"23","Vacant beds":"0","Last Updated":"29.04.2021"}]